tracegrep/__init__.py
tracegrep-0.1.1.dist-info/DESCRIPTION.rst
tracegrep-0.1.1.dist-info/METADATA
tracegrep-0.1.1.dist-info/RECORD
tracegrep-0.1.1.dist-info/WHEEL
tracegrep-0.1.1.dist-info/metadata.json
tracegrep-0.1.1.dist-info/top_level.txt
