Metadata-Version: 2.0
Name: tracegrep
Version: 0.1.1
Summary: Grep to parse Python traceback from plain text
Home-page: https://github.com/yixizhang/tracegrep
Author: Yixi Zhang
Author-email: yixi.zhang.max@gmail.com
License: MIT License
